arls.py
arls-2.1.0.dist-info/LICENSE.txt
arls-2.1.0.dist-info/METADATA
arls-2.1.0.dist-info/WHEEL
arls-2.1.0.dist-info/top_level.txt
arls-2.1.0.dist-info/RECORD
