Metadata-Version: 2.2
Name: arls
Version: 2.1.0
Summary: Autoregularized solver plus constraints for ill-conditioned linear systems of any shape.
Author-email: "Rondall E. Jones" <rejones7@msn.com>
Requires-Python: >=3.8
License-File: LICENSE.txt
